{"Breakfast": {"HOMESTYLE": ["Scrambled Eggs", "Vegetable Frittata", "Cinnamon French Toast", "Turkey Bacon", "Sweet Potato Tots", "Zucchini with Cherry Tomatoes", "Cream of Rice", "Meatless Vegetarian Sausage Patty"], "MY PANTRY EXHIBITION": ["Omelet Bar", "Eggs", "Egg Whites", "Chopped Spinach", "Chopped Broccoli ", "Chopped Tomatoes", " Diced Onions", "Sliced Mushrooms", "Chopped Green Bell Pepper", "Shredded Sharp Cheddar Cheese", "Crumbled Feta Cheese", "Pork Sausage Link", "Diced Bacon"], "BAKERY": ["Birthday Cake Glazed Doughnuts", "Strawberry Muffin"]}, "Lunch": {"HOMESTYLE": ["Baked Pollock", "Roasted Potatoes", "Sauteed Fresh Green Beans"], "HALAL": ["Baked Pollock", "Roasted Potatoes", "Sauteed Fresh Green Beans"], "DELICIOUS WITHOUT": ["BBQ Rotisserie Chicken", "Garlic Rice", "Carrot, Zucchini, Onion and Mushroom"], "ROOTED": ["Broccoli Tofu Stir Fry", "White Rice", "Sauteed Squash"], "GRILL": ["Roast Beef and Swiss", "Turkey Sloppy Joe", "French Fries", "Shredded Iceberg Lettuce", "Sliced Tomatoes", "Sliced Dill Pickles", "Sliced Red Onion"], "MY PANTRY EXHIBITION": ["Smokin' Hot Chipotle Chicken Wrap"], "DELI SPECIAL": ["Turkey Caprese Slider"], "THE KITCHEN PASTA BAR": ["Whole Wheat Rotini Pasta", "Penne Pasta", "Creamy Pesto Sauce", "Marinara Sauce"], "PIZZA STATION PASTA BAR": ["Feta and Tomato Pasta", "Penne Pasta", "Creamy Pesto Sauce"], "PIZZA/FLATBREADS": ["Cheese Pizza", "White Pesto Pea Pizza", "Chipotle BBQ Chicken Pizza", "Mushroom Pizza", "Crushed Red Pepper", "Dried Oregano", "Grated Parmesan Cheese", "Garlic Powder"], "SOUP STATION": ["New England Clam Chowder", "Three Bean Vegetable Minestrone", "Crackers, Saltine, 2 CT, Zesta"], "HUMMUS STATION": ["Carrot & Celery Sticks", "Hummus", "Basil Pesto Hummus", "Pita Chips"], "COMPOSED SALADS/GRAINS": [], "BAKERY": ["Vegan Oatmeal Raisin Cookie", "Lemon Meringue Pie", "Brownies with Powdered Sugar", "Peach Crisp", "Cheddar-Jalapeno Corn Bread Muffin"], "MADE TO ORDER DELI": ["Whole Wheat Kaiser Bun", "Multigrain Bread", "Whole Wheat Bread", "White Bread", "10\" Flour Tortilla", "10\" Whole Wheat Flour Tortilla", "Thinly Sliced Deli Turkey Breast", "Thinly Sliced Smoked Ham", "Falafel Ball", "Sliced American Cheese", "Cheddar Cheese Slice", "Sliced American Swiss Cheese", "Sliced Cucumber", "Sliced Green Bell Pepper", "Dill Pickle Slices", "Sliced Jalapeno Pepper", "Shredded Iceberg Lettuce", "Baby Spinach", "Sliced Tomatoes", "Sliced Red Onion", "House Fried Potato Chips ", "Classic Chicken Salad", "Roasted Red Pepper Hummus", "Housemade Italian Dressing", "Chipotle Mayo", "BBQ Ranch Dressing", "Roasted Chimichurri Cauliflower"], "THE MARKET": ["Romaine Blend", "Baby Spinach", "Lemon Couscous", "American Macaroni Salad", "Fresh Roasted Beets", "Roasted Jerk Cauliflower", "Herb Roasted Mushrooms", "Sliced Cucumber", "Cherry Tomatoes", "Shredded Carrots", "Sliced Red Onion", "Red and Green Bell Peppers", "Shredded Cheddar Cheese", "Crumbled Feta Cheese", "Grilled Herbed Chicken", "Chopped Hard Boiled Eggs", "Cilantro Pesto Tofu", "Harrissa Hummus", "Cajun Spiced Garbanzo Beans", "Ranch Dressing", "Blue Cheese Dressing", "Caesar Dressing", "Greek Feta Dressing", "Fat Free Italian Dressing", "Honey Mustard Dressing", "Sesame Dressing", "Balsamic Vinaigrette Dressing", "Extra Virgin Olive Oil", "Balsamic Vinegar", "Red Wine Vinegar", "Croutons", "Roasted Sunflower Seeds", "Dried Cranberries", "Chia Seeds"]}, "Dinner": {"HOMESTYLE": ["Old Bay Grilled Salmon", "Macaroni & Cheese", "Steamed Broccoli"], "HALAL": ["Old Bay Grilled Salmon", "Macaroni & Cheese", "Steamed Broccoli"], "DELICIOUS WITHOUT": ["Pork Stir Fry Bowl", "Pork in Marinade", "Filipino Garlic Fried Rice", "Stir Fry Vegetables", "Mongolian Sweet and Sour Sauce"], "ROOTED": ["Indian Spiced Chickpea Bowl", "Trinidad Paratha", "Mushroom Medley"], "GRILL": ["Turkey and Provolone Panini", "Fried Chicken Tenders", "Onion Rings", "Shredded Iceberg Lettuce", "Garlic Aioli", "Sliced Tomatoes"], "MY PANTRY EXHIBITION": [], "DELI SPECIAL": ["Turkey Caprese Slider"], "THE KITCHEN PASTA BAR": ["Whole Wheat Rotini Pasta", "Penne Pasta", "Creamy Pesto Sauce", "Marinara Sauce"], "PIZZA STATION PASTA BAR": ["Feta and Tomato Pasta", "Penne Pasta", "Creamy Pesto Sauce"], "PIZZA/FLATBREADS": ["Cheese Pizza", "White Pesto Pea Pizza", "Chipotle BBQ Chicken Pizza", "Mushroom Pizza", "Crushed Red Pepper", "Dried Oregano", "Grated Parmesan Cheese", "Garlic Powder"], "SOUP STATION": ["New England Clam Chowder", "Three Bean Vegetable Minestrone", "Crackers, Saltine, 2 CT, Zesta"], "HUMMUS STATION": ["Carrot & Celery Sticks", "Hummus", "Basil Pesto Hummus", "Pita Chips"], "COMPOSED SALADS/GRAINS": ["Sesame Ginger Farro Succotash Salad", "Roasted Vegetable Salad", "Grilled Sesame Tofu", "Paprika Roasted Cauliflower", "Blanched Broccoli", "Rosemary Roasted Mushroom", "Cooked Farro", "Pickled Green Beans"], "BAKERY": ["Froot Loop Cereal Bar", "Lemon Meringue Pie", "Brownies with Powdered Sugar", "Raspberry Vanilla topped Cheesecake", "Peach Crisp", "Cheddar-Jalapeno Corn Bread Muffin"], "MADE TO ORDER DELI": ["Whole Wheat Kaiser Bun", "Multigrain Bread", "Whole Wheat Bread", "White Bread", "10\" Flour Tortilla", "10\" Whole Wheat Flour Tortilla", "Thinly Sliced Deli Turkey Breast", "Thinly Sliced Smoked Ham", "Falafel Ball", "Sliced American Cheese", "Cheddar Cheese Slice", "Sliced American Swiss Cheese", "Sliced Cucumber", "Sliced Green Bell Pepper", "Dill Pickle Slices", "Sliced Jalapeno Pepper", "Shredded Iceberg Lettuce", "Baby Spinach", "Sliced Tomatoes", "Sliced Red Onion", "House Fried Potato Chips ", "Classic Chicken Salad", "Roasted Red Pepper Hummus", "Housemade Italian Dressing", "Chipotle Mayo", "BBQ Ranch Dressing", "Roasted Chimichurri Cauliflower"], "THE MARKET": ["Romaine Blend", "Baby Spinach", "Lemon Couscous", "American Macaroni Salad", "Fresh Roasted Beets", "Roasted Jerk Cauliflower", "Herb Roasted Mushrooms", "Sliced Cucumber", "Cherry Tomatoes", "Shredded Carrots", "Sliced Red Onion", "Red and Green Bell Peppers", "Shredded Cheddar Cheese", "Crumbled Feta Cheese", "Grilled Herbed Chicken", "Chopped Hard Boiled Eggs", "Cilantro Pesto Tofu", "Harrissa Hummus", "Cajun Spiced Garbanzo Beans", "Ranch Dressing", "Blue Cheese Dressing", "Caesar Dressing", "Greek Feta Dressing", "Fat Free Italian Dressing", "Honey Mustard Dressing", "Sesame Dressing", "Balsamic Vinaigrette Dressing", "Extra Virgin Olive Oil", "Balsamic Vinegar", "Red Wine Vinegar", "Croutons", "Roasted Sunflower Seeds", "Dried Cranberries", "Chia Seeds"]}}